zenllm/__init__.py
zenllm/__main__.py
zenllm/cli.py
zenllm/pricing.py
zenllm/test_orchestration.py
zenllm/providers/__init__.py
zenllm/providers/anthropic.py
zenllm/providers/base.py
zenllm/providers/deepseek.py
zenllm/providers/google.py
zenllm/providers/groq.py
zenllm/providers/openai.py
zenllm/providers/together.py
zenllm/providers/xai.py
zenllm-0.3.6.dist-info/licenses/LICENSE
zenllm-0.3.6.dist-info/METADATA
zenllm-0.3.6.dist-info/WHEEL
zenllm-0.3.6.dist-info/entry_points.txt
zenllm-0.3.6.dist-info/top_level.txt
zenllm-0.3.6.dist-info/RECORD
