Metadata-Version: 2.4
Name: zenllm
Version: 0.3.6
Summary: A zen, simple, and unified API to prompt LLMs from Anthropic, Google, OpenAI, and more, using only the requests library.
Home-page: https://koenvaneijk.com
Author: Koen van Eijk
Classifier: Programming Language :: Python :: 3
Classifier: License :: OSI Approved :: MIT License
Classifier: Operating System :: OS Independent
Classifier: Topic :: Scientific/Engineering :: Artificial Intelligence
Requires-Python: >=3.8
License-File: LICENSE
Requires-Dist: requests
Dynamic: author
Dynamic: classifier
Dynamic: description
Dynamic: description-content-type
Dynamic: home-page
Dynamic: license-file
Dynamic: requires-dist
Dynamic: requires-python
Dynamic: summary
